Metadata-Version: 2.4
Name: openlca-ipc
Version: 0.1.0
Summary: A Python library for interacting with openLCA desktop application through the IPC protocol for life cycle assessment (LCA) workflows.
Home-page: https://github.com/dernestbank/openlca-ipc
Author: Ernest Boakye Danquah
Author-email: Ernest Boakye Danquah <dernestbanksch@gmail.com>
License: MIT
Project-URL: Homepage, https://github.com/dernestbank/openlca-ipc
Project-URL: Documentation, https://github.com/dernestbank/openlca-ipc/tree/main/docs
Project-URL: Repository, https://github.com/dernestbank/openlca-ipc
Project-URL: Issues, https://github.com/dernestbank/openlca-ipc/issues
Keywords: openlca,lca,life-cycle-assessment,ipc,environmental-impact,iso-14040,iso-14044
Classifier: Development Status :: 4 - Beta
Classifier: Intended Audience :: Science/Research
Classifier: Topic :: Scientific/Engineering
Classifier: License :: OSI Approved :: MIT License
Classifier: Programming Language :: Python :: 3
Classifier: Programming Language :: Python :: 3.10
Classifier: Programming Language :: Python :: 3.11
Classifier: Programming Language :: Python :: 3.12
Classifier: Programming Language :: Python :: 3.13
Requires-Python: >=3.10
License-File: LICENSE
Requires-Dist: olca-ipc>=2.4.0
Requires-Dist: olca-schema>=2.4.0
Requires-Dist: numpy>=1.24.0
Provides-Extra: full
Requires-Dist: matplotlib>=3.7.0; extra == "full"
Requires-Dist: pandas>=2.0.0; extra == "full"
Requires-Dist: scipy>=1.10.0; extra == "full"
Provides-Extra: dev
Requires-Dist: pytest>=7.0.0; extra == "dev"
Requires-Dist: pytest-cov>=4.0.0; extra == "dev"
Requires-Dist: black>=23.0.0; extra == "dev"
Requires-Dist: flake8>=6.0.0; extra == "dev"
Requires-Dist: mypy>=1.0.0; extra == "dev"
Provides-Extra: viz
Requires-Dist: matplotlib>=3.7.0; extra == "viz"
Requires-Dist: seaborn>=0.12.0; extra == "viz"
Provides-Extra: export
Requires-Dist: pandas>=2.0.0; extra == "export"
Requires-Dist: openpyxl>=3.1.0; extra == "export"
Dynamic: author
Dynamic: home-page
Dynamic: license-file
Dynamic: requires-python
